qg_struct/MemoryDB.py
qg_struct/RelationalDB.py
qg_struct/__init__.py
qg_struct/config.py
qg_struct/log.py
qg_struct-1.0.1.dist-info/METADATA
qg_struct-1.0.1.dist-info/WHEEL
qg_struct-1.0.1.dist-info/top_level.txt
qg_struct-1.0.1.dist-info/RECORD
