Metadata-Version: 2.1
Name: qg-struct
Version: 1.0.1
Summary: 全高底层框架封装
Home-page: http://192.168.117.144/cetc28/spiderStructFrameWork
Author: zouwendi
Author-email: tz310200@gamil.com
Maintainer: zouwendi
Maintainer-email: tz310200@gamil.com
License: GPL3 License
Platform: all
Classifier: Development Status :: 4 - Beta
Classifier: Operating System :: OS Independent
Classifier: Intended Audience :: Developers
Classifier: Programming Language :: Python
Classifier: Programming Language :: Python :: Implementation
Classifier: Programming Language :: Python :: 3
Classifier: Programming Language :: Python :: 3.4
Classifier: Programming Language :: Python :: 3.5
Classifier: Programming Language :: Python :: 3.5
Classifier: Programming Language :: Python :: 3.6
Classifier: Programming Language :: Python :: 3.7
Classifier: Topic :: Software Development :: Libraries
Requires-Dist: python-logstash (>=0.4.6)
Requires-Dist: colorama (>=0.4.1)
Requires-Dist: setuptools (>=41.0.1)
Requires-Dist: aioredis (>=1.2.0)
Requires-Dist: termcolor (>=1.1.0)
Requires-Dist: pytest (>=4.0.2)
Requires-Dist: aiohttp (>=3.5.4)
Requires-Dist: pipreqs (>=0.4.9)
Requires-Dist: qg-aio-eureka (>=0.1.2)
